{
  "volume": "第15卷",
  "title": "第15卷",
  "_comment": "从目录页自动生成，请人工检查",
  "sections": [
    {
      "name": "卡·马克思。为拿破仑在莱茵河上的未来战争作准备",
      "page_start": 53,
      "page_end": 62
    },
    {
      "name": "卡·马克思。加里波第在西西里。——普鲁士的状况",
      "page_start": 63,
      "page_end": 68
    },
    {
      "name": "拉法里纳之争。——加里波第的信",
      "page_start": 100,
      "page_end": 104
    },
    {
      "name": "弗·恩格斯。不列颠的国防",
      "page_start": 105,
      "page_end": 109
    },
    {
      "name": "弗·恩格斯。伦敦会不会落入法国人之手？",
      "page_start": 115,
      "page_end": 120
    },
    {
      "name": "卡·马克思。俄法同盟",
      "page_start": 121,
      "page_end": 126
    },
    {
      "name": "卡·马克思。纸张税。——皇帝的信",
      "page_start": 127,
      "page_end": 131
    },
    {
      "name": "弗·恩格斯。加里波第的运动",
      "page_start": 132,
      "page_end": 135
    },
    {
      "name": "法国公债和印度公债",
      "page_start": 136,
      "page_end": 140
    },
    {
      "name": "弗·恩格斯。奥地利病夫",
      "page_start": 141,
      "page_end": 144
    },
    {
      "name": "卡·马克思。欧洲的收成",
      "page_start": 145,
      "page_end": 148
    },
    {
      "name": "弗·恩格斯。英国志愿兵猎兵的检阅",
      "page_start": 149,
      "page_end": 156
    },
    {
      "name": "备战。——东方问题",
      "page_start": 157,
      "page_end": 162
    },
    {
      "name": "弗·恩格斯。加里波第在卡拉布里亚",
      "page_start": 168,
      "page_end": 171
    },
    {
      "name": "卡·马克思。俄国利用奥地利。——华沙会议",
      "page_start": 192,
      "page_end": 195
    },
    {
      "name": "意大利",
      "page_start": 196,
      "page_end": 200
    },
    {
      "name": "弗·恩格斯。步枪史",
      "page_start": 209,
      "page_end": 241
    },
    {
      "name": "弗·恩格斯。志愿兵工兵，他们的作用和活动范围……244－",
      "page_start": 248,
      "page_end": 248
    },
    {
      "name": "弗·恩格斯。奥地利革命的发展",
      "page_start": 249,
      "page_end": 252
    },
    {
      "name": "弗·恩格斯。德国的运动",
      "page_start": 253,
      "page_end": 256
    },
    {
      "name": "弗·恩格斯。法国的武装力量",
      "page_start": 257,
      "page_end": 261
    },
    {
      "name": "弗·恩格斯。毕若元帅论战斗中的精神因素",
      "page_start": 262,
      "page_end": 270
    },
    {
      "name": "弗·恩格斯。“志愿兵读物”单行本序言",
      "page_start": 273,
      "page_end": 273
    },
    {
      "name": "弗·恩格斯。布莱顿和温伯耳登",
      "page_start": 280,
      "page_end": 286
    },
    {
      "name": "弗·恩格斯。连队列教练",
      "page_start": 287,
      "page_end": 292
    },
    {
      "name": "弗·恩格斯。步枪和步枪射击",
      "page_start": 293,
      "page_end": 298
    },
    {
      "name": "卡·马克思。伦敦“泰晤士报”和帕麦斯顿勋爵",
      "page_start": 335,
      "page_end": 340
    },
    {
      "name": "卡·马克思。伦敦“泰晤士报”评奥尔良亲王赴美",
      "page_start": 341,
      "page_end": 345
    },
    {
      "name": "卡·马克思。英国的危机",
      "page_start": 367,
      "page_end": 370
    },
    {
      "name": "卡·马克思。经济短评",
      "page_start": 377,
      "page_end": 380
    },
    {
      "name": "卡·马克思。对墨西哥的干涉",
      "page_start": 381,
      "page_end": 385
    },
    {
      "name": "卡·马克思。对墨西哥的干涉",
      "page_start": 386,
      "page_end": 393
    },
    {
      "name": "卡·马克思。富尔德先生",
      "page_start": 394,
      "page_end": 396
    },
    {
      "name": "卡·马克思。弗里芒特的免职",
      "page_start": 401,
      "page_end": 403
    },
    {
      "name": "弗·恩格斯。志愿兵军官",
      "page_start": 404,
      "page_end": 407
    },
    {
      "name": "卡·马克思。“特伦特号”事件",
      "page_start": 408,
      "page_end": 411
    },
    {
      "name": "卡·马克思。英美的冲突",
      "page_start": 412,
      "page_end": 415
    },
    {
      "name": "卡·马克思。“特伦特号”事件的消息和伦敦的反应",
      "page_start": 416,
      "page_end": 421
    },
    {
      "name": "弗·恩格斯。美国战争的教训",
      "page_start": 422,
      "page_end": 426
    },
    {
      "name": "卡·马克思。“特伦特号”剧中的几位主角",
      "page_start": 427,
      "page_end": 430
    },
    {
      "name": "卡·马克思。英国国内同情心的增长",
      "page_start": 437,
      "page_end": 441
    },
    {
      "name": "卡·马克思。奴隶制问题的危机",
      "page_start": 442,
      "page_end": 443
    },
    {
      "name": "卡·马克思。一件诽谤案",
      "page_start": 447,
      "page_end": 450
    },
    {
      "name": "卡·马克思。华盛顿政府与西方列强",
      "page_start": 451,
      "page_end": 453
    },
    {
      "name": "卡·马克思。报刊的意见和人民的意见",
      "page_start": 454,
      "page_end": 457
    },
    {
      "name": "卡·马克思。法国的新闻敲诈。——战争的经济后果",
      "page_start": 458,
      "page_end": 459
    },
    {
      "name": "卡·马克思。一个同情美国的大会",
      "page_start": 460,
      "page_end": 462
    },
    {
      "name": "卡·马克思。西华德的公文被隐匿的经过",
      "page_start": 470,
      "page_end": 471
    },
    {
      "name": "卡·马克思。铁路统计资料",
      "page_start": 472,
      "page_end": 475
    },
    {
      "name": "卡·马克思。约翰·罗素勋爵的一次政变",
      "page_start": 476,
      "page_end": 479
    },
    {
      "name": "卡·马克思。伦敦的工人大会",
      "page_start": 480,
      "page_end": 483
    },
    {
      "name": "卡·马克思。关于棉纺织工业的危机",
      "page_start": 487,
      "page_end": 489
    },
    {
      "name": "卡·马克思。墨西哥的混乱",
      "page_start": 499,
      "page_end": 504
    },
    {
      "name": "封锁被承认",
      "page_start": 509,
      "page_end": 512
    },
    {
      "name": "卡·马克思。国际性的米勒斯案",
      "page_start": 524,
      "page_end": 526
    },
    {
      "name": "卡·马克思。英国报刊与新奥尔良的陷落",
      "page_start": 527,
      "page_end": 530
    },
    {
      "name": "卡·马克思和弗·恩格斯。美国战场的形势",
      "page_start": 533,
      "page_end": 537
    },
    {
      "name": "卡·马克思。一场丑剧",
      "page_start": 549,
      "page_end": 552
    },
    {
      "name": "法国的联盟",
      "page_start": 553,
      "page_end": 555
    },
    {
      "name": "卡·马克思。评美国局势",
      "page_start": 556,
      "page_end": 559
    },
    {
      "name": "卡·马克思。美国废奴派的示威",
      "page_start": 563,
      "page_end": 566
    },
    {
      "name": "弗·恩格斯。英国的志愿兵检阅",
      "page_start": 567,
      "page_end": 573
    },
    {
      "name": "卡·马克思。援救加里波第大会",
      "page_start": 574,
      "page_end": 576
    },
    {
      "name": "卡·马克思。英国工人的贫困",
      "page_start": 577,
      "page_end": 580
    },
    {
      "name": "的贫困",
      "page_start": 581,
      "page_end": 583
    },
    {
      "name": "卡·马克思。北美事件",
      "page_start": 584,
      "page_end": 587
    },
    {
      "name": "卡·马克思。北美形势",
      "page_start": 592,
      "page_end": 595
    },
    {
      "name": "卡·马克思。南部同盟势穷力竭的迹象",
      "page_start": 596,
      "page_end": 599
    },
    {
      "name": "卡·马克思。英国的中立。——南部各州的状况607",
      "page_start": 609,
      "page_end": 609
    },
    {
      "name": "卡·马克思。给“柏林改革报”编辑部的信",
      "page_start": 613,
      "page_end": 613
    },
    {
      "name": "的呼吁书",
      "page_start": 614,
      "page_end": 615
    },
    {
      "name": "弗·恩格斯。什列斯维希的军队人数",
      "page_start": 616,
      "page_end": 618
    },
    {
      "name": "费·恩格斯。英国的反德兵力",
      "page_start": 619,
      "page_end": 624
    },
    {
      "name": "卡·马克思和弗·恩格斯生平事业年表",
      "page_start": 749,
      "page_end": 774
    },
    {
      "name": "人名索引",
      "page_start": 775,
      "page_end": 821
    },
    {
      "name": "期刊索引",
      "page_start": 813,
      "page_end": 816
    },
    {
      "name": "地名索引",
      "page_start": 817,
      "page_end": 286
    },
    {
      "name": "译后记",
      "page_start": 827,
      "page_end": 827
    },
    {
      "name": "内战前夕的美利坚合众国图（1861—186年5）",
      "page_start": 358,
      "page_end": 359
    },
    {
      "name": "……………………………520—521美国内战的进程图（1861—186）",
      "page_start": 2,
      "page_end": 2
    },
    {
      "name": "一大组论文就是用来论述美国历史上的重要事件即",
      "page_start": 1861,
      "page_end": 1865
    },
    {
      "name": "了马克思主义奠基人的预见的正确性。马克思和恩格斯于",
      "page_start": 1861,
      "page_end": 1861
    },
    {
      "name": "人阶级的血汗，谁应该最少地援助贫困的工人”（见本卷第",
      "page_start": 579,
      "page_end": 579
    }
  ]
}