{
  "volume": "第19卷",
  "title": "第19卷",
  "_comment": "从目录页自动生成，请人工检查",
  "sections": [
    {
      "name": "弗·恩格斯。给奥·倍倍尔的信",
      "page_start": 3,
      "page_end": 10
    },
    {
      "name": "卡·马克思。哥达纲领批判",
      "page_start": 11,
      "page_end": 35
    },
    {
      "name": "给威·白拉克的信",
      "page_start": 13,
      "page_end": 14
    },
    {
      "name": "对德国工人党纲领的几点意见",
      "page_start": 15,
      "page_end": 35
    },
    {
      "name": "……………………………………………………………一",
      "page_start": 15,
      "page_end": 15
    },
    {
      "name": "……………………………………………………………二",
      "page_start": 26,
      "page_end": 26
    },
    {
      "name": "……………………………………………………………三",
      "page_start": 28,
      "page_end": 28
    },
    {
      "name": "……………………………………………………………四",
      "page_start": 30,
      "page_end": 30
    },
    {
      "name": "弗·恩格斯。给纽约国际工人协会总委员会的信",
      "page_start": 36,
      "page_end": 38
    },
    {
      "name": "弗·恩格斯。在一八六三年波兰起义纪念会上的演说",
      "page_start": 39,
      "page_end": 40
    },
    {
      "name": "弗·恩格斯。德意志帝国国会中的普鲁士烧酒",
      "page_start": 41,
      "page_end": 59
    },
    {
      "name": "…………………………………………………………一",
      "page_start": 43,
      "page_end": 53
    },
    {
      "name": "…………………………………………………………二",
      "page_start": 54,
      "page_end": 59
    },
    {
      "name": "弗·恩格斯。威廉·沃尔弗",
      "page_start": 61,
      "page_end": 106
    },
    {
      "name": "…………………………………………………………一",
      "page_start": 64,
      "page_end": 67
    },
    {
      "name": "…………………………………………………………二",
      "page_start": 68,
      "page_end": 71
    },
    {
      "name": "…………………………………………………………三",
      "page_start": 72,
      "page_end": 75
    },
    {
      "name": "…………………………………………………………四",
      "page_start": 76,
      "page_end": 78
    },
    {
      "name": "…………………………………………………………五",
      "page_start": 79,
      "page_end": 82
    },
    {
      "name": "…………………………………………………………  六",
      "page_start": 83,
      "page_end": 87
    },
    {
      "name": "…………………………………………………………七",
      "page_start": 88,
      "page_end": 91
    },
    {
      "name": "…………………………………………………………八",
      "page_start": 92,
      "page_end": 96
    },
    {
      "name": "………………………………………………………九",
      "page_start": 97,
      "page_end": 100
    },
    {
      "name": "………………………………………………………十",
      "page_start": 101,
      "page_end": 103
    },
    {
      "name": "……………………………………………………十一",
      "page_start": 104,
      "page_end": 106
    },
    {
      "name": "给恩·比尼亚米的信",
      "page_start": 107,
      "page_end": 109
    },
    {
      "name": "弗·恩格斯。意大利的情况",
      "page_start": 110,
      "page_end": 114
    },
    {
      "name": "弗·恩格斯。卡尔·马克思",
      "page_start": 115,
      "page_end": 125
    },
    {
      "name": "卡·马克思。给“祖国纪事”杂志编辑部的信",
      "page_start": 126,
      "page_end": 131
    },
    {
      "name": "弗·恩格斯。……德国、法国、美国和俄国的工人运动",
      "page_start": 132,
      "page_end": 134
    },
    {
      "name": "弗·恩格斯。一八七七年的欧洲工人",
      "page_start": 135,
      "page_end": 158
    },
    {
      "name": "………………………………………………………一",
      "page_start": 137,
      "page_end": 140
    },
    {
      "name": "………………………………………………………二",
      "page_start": 141,
      "page_end": 144
    },
    {
      "name": "………………………………………………………三",
      "page_start": 145,
      "page_end": 149
    },
    {
      "name": "………………………………………………………四",
      "page_start": 150,
      "page_end": 154
    },
    {
      "name": "………………………………………………………五",
      "page_start": 155,
      "page_end": 158
    },
    {
      "name": "卡·马克思。布赫尔先生",
      "page_start": 159,
      "page_end": 160
    },
    {
      "name": "卡·马克思。………………………答布赫尔的“说明”",
      "page_start": 161,
      "page_end": 162
    },
    {
      "name": "卡·马克思。乔治·豪威耳先生的国际工人协会史",
      "page_start": 163,
      "page_end": 169
    },
    {
      "name": "状况",
      "page_start": 170,
      "page_end": 171
    },
    {
      "name": "威·李卜克内西、威·白拉克等人的通告信",
      "page_start": 172,
      "page_end": 190
    },
    {
      "name": "一、同卡·希尔施的谈判",
      "page_start": 172,
      "page_end": 172
    },
    {
      "name": "二、给报纸拟定的方针",
      "page_start": 178,
      "page_end": 178
    },
    {
      "name": "………………………………………三、苏黎世三人团的宣言",
      "page_start": 182,
      "page_end": 182
    },
    {
      "name": "弗·恩格斯。俾斯麦先生的社会主义",
      "page_start": 191,
      "page_end": 200
    },
    {
      "name": "一、关税率",
      "page_start": 191,
      "page_end": 191
    },
    {
      "name": "…………………………………………………二、国有铁路",
      "page_start": 196,
      "page_end": 196
    },
    {
      "name": "弗·恩格斯。社会主义从空想到科学的发展",
      "page_start": 201,
      "page_end": 247
    },
    {
      "name": "一",
      "page_start": 205,
      "page_end": 218
    },
    {
      "name": "………………………………………………………三",
      "page_start": 228,
      "page_end": 247
    },
    {
      "name": "卡·马克思。关于“哲学的贫困”",
      "page_start": 248,
      "page_end": 249
    },
    {
      "name": "卡·马克思。工人调查表",
      "page_start": 250,
      "page_end": 258
    },
    {
      "name": "一",
      "page_start": 250,
      "page_end": 250
    },
    {
      "name": "……………………………………………………………四",
      "page_start": 256,
      "page_end": 256
    },
    {
      "name": "空想到科学的发展”法文版导言",
      "page_start": 259,
      "page_end": 263
    },
    {
      "name": "卡·马克思。……………………………法国工人党纲领导言",
      "page_start": 264,
      "page_end": 264
    },
    {
      "name": "波兰革命五十周年纪念大会",
      "page_start": 265,
      "page_end": 267
    },
    {
      "name": "卡·马克思。给维·伊·查苏利奇的信",
      "page_start": 268,
      "page_end": 269
    },
    {
      "name": "…………卡·马克思和弗·恩格斯。给“每日新闻”编辑的信",
      "page_start": 272,
      "page_end": 272
    },
    {
      "name": "弗·恩格斯。做一天公平的工作，得一天公平的工资",
      "page_start": 273,
      "page_end": 276
    },
    {
      "name": "弗·恩格斯。雇佣劳动制度",
      "page_start": 277,
      "page_end": 279
    },
    {
      "name": "弗·恩格斯。工联",
      "page_start": 280,
      "page_end": 286
    },
    {
      "name": "……………………………………………………………一",
      "page_start": 280,
      "page_end": 280
    },
    {
      "name": "……………………………………………………………二",
      "page_start": 283,
      "page_end": 283
    },
    {
      "name": "弗·恩格斯。对法国的通商条约",
      "page_start": 287,
      "page_end": 291
    },
    {
      "name": "弗·恩格斯。两个模范地方议会",
      "page_start": 292,
      "page_end": 295
    },
    {
      "name": "弗·恩格斯。美国的食品和土地问题",
      "page_start": 296,
      "page_end": 298
    },
    {
      "name": "弗·恩格斯。反谷物法同盟的工资理论",
      "page_start": 299,
      "page_end": 303
    },
    {
      "name": "弗·恩格斯。工人党",
      "page_start": 304,
      "page_end": 307
    },
    {
      "name": "弗·恩格斯。俾斯麦和德国工人党",
      "page_start": 308,
      "page_end": 310
    },
    {
      "name": "弗·恩格斯。棉花和铁",
      "page_start": 311,
      "page_end": 314
    },
    {
      "name": "弗·恩格斯。必要的和多余的社会阶级",
      "page_start": 315,
      "page_end": 318
    },
    {
      "name": "弗·恩格斯。燕妮·马克思（冯·威斯特华伦）",
      "page_start": 319,
      "page_end": 321
    },
    {
      "name": "弗·恩格斯。在燕妮·马克思墓前的讲话",
      "page_start": 322,
      "page_end": 324
    },
    {
      "name": "俄文第二版序言",
      "page_start": 325,
      "page_end": 326
    },
    {
      "name": "弗·恩格斯。布鲁诺·鲍威尔和早期基督教",
      "page_start": 327,
      "page_end": 336
    },
    {
      "name": "弗·恩格斯。论美国资本的积聚",
      "page_start": 337,
      "page_end": 339
    },
    {
      "name": "弗·恩格斯。布雷的牧师",
      "page_start": 340,
      "page_end": 344
    },
    {
      "name": "德文本初版序言",
      "page_start": 345,
      "page_end": 347
    },
    {
      "name": "弗·恩格斯。品特是怎样造谣的",
      "page_start": 348,
      "page_end": 350
    },
    {
      "name": "弗·恩格斯。马尔克",
      "page_start": 351,
      "page_end": 369
    },
    {
      "name": "……………………弗·恩格斯。燕妮·龙格（马克思）",
      "page_start": 370,
      "page_end": 371
    },
    {
      "name": "弗·恩格斯。马克思墓前悼词草稿",
      "page_start": 372,
      "page_end": 373
    },
    {
      "name": "弗·恩格斯。卡尔·马克思的葬仪",
      "page_start": 374,
      "page_end": 379
    },
    {
      "name": "弗·恩格斯。卡尔·马克思的逝世",
      "page_start": 380,
      "page_end": 388
    },
    {
      "name": "……………………………………………………………一",
      "page_start": 380,
      "page_end": 380
    },
    {
      "name": "……………………………………………………………二",
      "page_start": 383,
      "page_end": 383
    },
    {
      "name": "卡·马克思。评阿·瓦格纳的“政治经济学教科书”",
      "page_start": 396,
      "page_end": 429
    },
    {
      "name": "卡·马克思。给维·伊·查苏利奇的复信草稿",
      "page_start": 430,
      "page_end": 452
    },
    {
      "name": "……………………………………………………初稿",
      "page_start": 430,
      "page_end": 441
    },
    {
      "name": "……………………………………………………二稿",
      "page_start": 442,
      "page_end": 446
    },
    {
      "name": "……………………………………………………三稿",
      "page_start": 447,
      "page_end": 452
    },
    {
      "name": "发展的札记",
      "page_start": 453,
      "page_end": 477
    },
    {
      "name": "…………………………………… ［准备改革的］过程",
      "page_start": 453,
      "page_end": 453
    },
    {
      "name": "………………………… ［编纂委员会工作的三个时期］",
      "page_start": 456,
      "page_end": 456
    },
    {
      "name": "…………………………………………… 地方自治机关",
      "page_start": 463,
      "page_end": 463
    },
    {
      "name": "…………………………………………………… 俄国",
      "page_start": 471,
      "page_end": 471
    },
    {
      "name": "弗·恩格斯。论日耳曼人的古代历史",
      "page_start": 478,
      "page_end": 538
    },
    {
      "name": "…………………………………………………凯撒和塔西佗",
      "page_start": 478,
      "page_end": 478
    },
    {
      "name": "……………………………………………和罗马的最初战斗",
      "page_start": 493,
      "page_end": 493
    },
    {
      "name": "………………………………………民族大迁徙以前的进步",
      "page_start": 509,
      "page_end": 509
    },
    {
      "name": "…………………………………………注释：各日耳曼部落",
      "page_start": 523,
      "page_end": 523
    },
    {
      "name": "…………………………………弗·恩格斯。法兰克时代",
      "page_start": 539,
      "page_end": 599
    },
    {
      "name": "…………………墨洛温王朝和卡罗林王朝的土地关系的变革",
      "page_start": 539,
      "page_end": 539
    },
    {
      "name": "……………………………………………区制度和军事制度",
      "page_start": 552,
      "page_end": 552
    },
    {
      "name": "……………………………………………注释：法兰克方言",
      "page_start": 564,
      "page_end": 564
    },
    {
      "name": "注释",
      "page_start": 603,
      "page_end": 663
    },
    {
      "name": "卡·马克思和弗·恩格斯生平事业年表",
      "page_start": 664,
      "page_end": 696
    },
    {
      "name": "人名索引",
      "page_start": 697,
      "page_end": 724
    },
    {
      "name": "期刊索引",
      "page_start": 725,
      "page_end": 727
    },
    {
      "name": "地名索引",
      "page_start": 728,
      "page_end": 740
    },
    {
      "name": "度量衡和货币名称表",
      "page_start": 741,
      "page_end": 741
    },
    {
      "name": "译后记",
      "page_start": 742,
      "page_end": 745
    },
    {
      "name": "卡·马克思给“祖国纪事”杂志编辑部的信的第一页",
      "page_start": 127,
      "page_end": 127
    },
    {
      "name": "卡·马克思和弗·恩格斯的通告信的第一页",
      "page_start": 173,
      "page_end": 173
    },
    {
      "name": "第一版的扉页",
      "page_start": 203,
      "page_end": 203
    },
    {
      "name": "科学的发展”法文版所写的导言的最后一页",
      "page_start": 261,
      "page_end": 261
    },
    {
      "name": "弗·恩格斯“论日耳曼人的古代历史”一文中日耳曼人移住图",
      "page_start": 531,
      "page_end": 531
    },
    {
      "name": "1875年月3—1883年月",
      "page_start": 5,
      "page_end": 5
    }
  ]
}