{
  "volume": "第21卷",
  "title": "第21卷",
  "_comment": "仅一级目录，从目录页自动生成，请人工检查",
  "sections": [
    {
      "name": "“共产党宣言”1883年德文版序言",
      "page_start": 3,
      "page_end": 4
    },
    {
      "name": "格奥尔格·维尔特。格奥尔格·维尔特的“帮工之歌”（1846年）",
      "page_start": 5,
      "page_end": 9
    },
    {
      "name": "启示录",
      "page_start": 10,
      "page_end": 16
    },
    {
      "name": "马克思和“新莱茵报”（1848—1849年）",
      "page_start": 17,
      "page_end": 26
    },
    {
      "name": "家庭、私有制和国家的起源。就路易斯·亨·摩尔根的研究成果而作",
      "page_start": 27,
      "page_end": 203
    },
    {
      "name": "卡·马克思“雇佣劳动与资本”一书1884年单行本前言",
      "page_start": 204,
      "page_end": 204
    },
    {
      "name": "马克思和洛贝尔图斯。卡·马克思“哲学的贫困”一书德文第一版序言",
      "page_start": 205,
      "page_end": 220
    },
    {
      "name": "帝俄高级炸药顾问",
      "page_start": 221,
      "page_end": 223
    },
    {
      "name": "一八四五年和一八八五年的英国",
      "page_start": 224,
      "page_end": 231
    },
    {
      "name": "“卡尔·马克思在科伦陪审法庭面前”一书序言",
      "page_start": 232,
      "page_end": 239
    },
    {
      "name": "致“北方通报”杂志编辑部",
      "page_start": 240,
      "page_end": 240
    },
    {
      "name": "关于共产主义者同盟的历史",
      "page_start": 241,
      "page_end": 261
    },
    {
      "name": "当前的形势",
      "page_start": 262,
      "page_end": 263
    },
    {
      "name": "致“社会主义者报”编辑委员会",
      "page_start": 264,
      "page_end": 265
    },
    {
      "name": "不应该这样翻译马克思的著作",
      "page_start": 266,
      "page_end": 278
    },
    {
      "name": "关于普鲁士农民的历史。威·沃尔弗的小册子“西里西亚的十亿”的导言",
      "page_start": 279,
      "page_end": 289
    },
    {
      "name": "卡·马克思“路易·波拿巴的雾月十八日”一书德文第三版序言",
      "page_start": 290,
      "page_end": 291
    },
    {
      "name": "“英国工人阶级状况”美国版附录",
      "page_start": 292,
      "page_end": 298
    },
    {
      "name": "纪念巴黎公社十五周年",
      "page_start": 299,
      "page_end": 300
    },
    {
      "name": "路德维希·费尔巴哈和德国古典哲学的终结",
      "page_start": 301,
      "page_end": 353
    },
    {
      "name": "给“纽约人民报”编辑部的声明",
      "page_start": 354,
      "page_end": 354
    },
    {
      "name": "关于里昂玻璃厂工人的罢工",
      "page_start": 355,
      "page_end": 355
    },
    {
      "name": "欧洲政局",
      "page_start": 356,
      "page_end": 364
    },
    {
      "name": "约翰·菲力浦·贝克尔",
      "page_start": 365,
      "page_end": 371
    },
    {
      "name": "“论住宅问题”一书第二版序言",
      "page_start": 372,
      "page_end": 382
    },
    {
      "name": "美国工人运动。“英国工人阶级状况”美国版序言",
      "page_start": 383,
      "page_end": 392
    },
    {
      "name": "给巴黎国际联谊节组织委员会的信",
      "page_start": 393,
      "page_end": 395
    },
    {
      "name": "波克罕“纪念一八○六至一八○七年德意志极端爱国主义者”一书引言",
      "page_start": 396,
      "page_end": 402
    },
    {
      "name": "“共产党宣言”1888年英文版序言",
      "page_start": 403,
      "page_end": 410
    },
    {
      "name": "“路德维希·费尔巴哈和德国古典哲学的终结”一书序言",
      "page_start": 411,
      "page_end": 412
    },
    {
      "name": "保护关税制度和自由贸易。卡尔·马克思的小册子“关于自由贸易的演说”的序言",
      "page_start": 413,
      "page_end": 431
    },
    {
      "name": "1889鲁年尔矿工的罢工",
      "page_start": 432,
      "page_end": 434
    },
    {
      "name": "可能派的代表资格证",
      "page_start": 435,
      "page_end": 437
    },
    {
      "name": "关于伦敦码头工人的罢工",
      "page_start": 438,
      "page_end": 438
    },
    {
      "name": "资产阶级让位了",
      "page_start": 439,
      "page_end": 446
    },
    {
      "name": "论未来的联合体",
      "page_start": 447,
      "page_end": 447
    },
    {
      "name": "论封建制度的瓦解和民族国家的产生",
      "page_start": 448,
      "page_end": 458
    },
    {
      "name": "关于“农民战争”",
      "page_start": 459,
      "page_end": 460
    },
    {
      "name": "暴力在历史中的作用",
      "page_start": 461,
      "page_end": 527
    },
    {
      "name": "小册子“暴力在历史中的作用”序言草稿",
      "page_start": 528,
      "page_end": 528
    },
    {
      "name": "小册子“暴力在历史中的作用”第四章提纲",
      "page_start": 529,
      "page_end": 530
    },
    {
      "name": "小册子“暴力在历史中的作用”第四章结束部分提纲",
      "page_start": 531,
      "page_end": 533
    },
    {
      "name": "美国旅行印象",
      "page_start": 534,
      "page_end": 538
    },
    {
      "name": "附  录格·亚·洛帕廷给玛·尼·奥沙尼娜的信的片断",
      "page_start": 539,
      "page_end": 541
    },
    {
      "name": "1849年的五月起义",
      "page_start": 542,
      "page_end": 544
    },
    {
      "name": "法学家的社会主义",
      "page_start": 545,
      "page_end": 568
    },
    {
      "name": "弗·恩格斯对英国北方社会主义联盟纲领的修正",
      "page_start": 569,
      "page_end": 570
    },
    {
      "name": "弗·恩格斯修改的英国北方社会主义联盟纲领",
      "page_start": 570,
      "page_end": 571
    },
    {
      "name": "恩格斯同“纽约人民报”编辑部的谈话",
      "page_start": 571,
      "page_end": 572
    },
    {
      "name": "188年国际工人代表大会。答“正议报”",
      "page_start": 573,
      "page_end": 585
    },
    {
      "name": "给“工人选民”报编辑部的信",
      "page_start": 586,
      "page_end": 587
    },
    {
      "name": "国际社会主义工人代表大会（1889年月714—2日1）。告欧美工人和社会主义者书",
      "page_start": 588,
      "page_end": 590
    },
    {
      "name": "1889年国际工人代表大会。．答“社会民主联盟宣言”",
      "page_start": 591,
      "page_end": 612
    },
    {
      "name": "组织委员会关于召开国际社会主义工人代表大会的通知书",
      "page_start": 613,
      "page_end": 618
    },
    {
      "name": "注释",
      "page_start": 619,
      "page_end": 726
    },
    {
      "name": "弗·恩格斯生平事业年表",
      "page_start": 727,
      "page_end": 766
    },
    {
      "name": "人名索引",
      "page_start": 767,
      "page_end": 809
    },
    {
      "name": "期刊索引",
      "page_start": 810,
      "page_end": 811
    },
    {
      "name": "地名索引",
      "page_start": 812,
      "page_end": 819
    },
    {
      "name": "“家庭、私有制和国家的起源”一书族名索引",
      "page_start": 820,
      "page_end": 826
    },
    {
      "name": "译后记",
      "page_start": 827,
      "page_end": 828
    }
  ]
}