{
  "volume": "第25卷（上）",
  "title": "第25卷",
  "_comment": "从目录页自动生成，请人工检查",
  "sections": [
    {
      "name": "弗里德里希·恩格斯 序言",
      "page_start": 3,
      "page_end": 26
    },
    {
      "name": "第一章 成本价格和利润",
      "page_start": 29,
      "page_end": 48
    },
    {
      "name": "第二章 利润率",
      "page_start": 49,
      "page_end": 57
    },
    {
      "name": "第三章 利润率和剩余价值率的关系",
      "page_start": 58,
      "page_end": 83
    },
    {
      "name": "第四章 周转对利润率的影响",
      "page_start": 84,
      "page_end": 91
    },
    {
      "name": "第五章 不变资本使用上的节约",
      "page_start": 92,
      "page_end": 120
    },
    {
      "name": "第六章 价格变动的影响",
      "page_start": 121,
      "page_end": 154
    },
    {
      "name": "．原料价格的波动及其对利润率的直接影响",
      "page_start": 121,
      "page_end": 121
    },
    {
      "name": "．资本的增值和贬值、游离和束缚",
      "page_start": 126,
      "page_end": 126
    },
    {
      "name": "．一般的例证：1861—186年5的棉业危机",
      "page_start": 141,
      "page_end": 141
    },
    {
      "name": "第七章 补充说明",
      "page_start": 155,
      "page_end": 158
    },
    {
      "name": "的利润率的差别",
      "page_start": 159,
      "page_end": 172
    },
    {
      "name": "转化为生产价格",
      "page_start": 173,
      "page_end": 192
    },
    {
      "name": "市场价值。超额利润",
      "page_start": 193,
      "page_end": 222
    },
    {
      "name": "第十一章 工资的一般变动对生产价格的影响",
      "page_start": 223,
      "page_end": 227
    },
    {
      "name": "第十二章 补充说明",
      "page_start": 228,
      "page_end": 234
    },
    {
      "name": "．引起生产价格变化的原因",
      "page_start": 228,
      "page_end": 228
    },
    {
      "name": "．中等构成的商品的生产价格",
      "page_start": 230,
      "page_end": 230
    },
    {
      "name": "．资本家的补偿理由",
      "page_start": 231,
      "page_end": 231
    },
    {
      "name": "第十三章 规律本身",
      "page_start": 235,
      "page_end": 257
    },
    {
      "name": "第十四章 起反作用的各种原因",
      "page_start": 258,
      "page_end": 268
    },
    {
      "name": "．劳动剥削程度的提高",
      "page_start": 258,
      "page_end": 258
    },
    {
      "name": "．工资被压低到劳动力的价值以下",
      "page_start": 262,
      "page_end": 262
    },
    {
      "name": "．相对过剩人口",
      "page_start": 263,
      "page_end": 263
    },
    {
      "name": "．对外贸易",
      "page_start": 264,
      "page_end": 264
    },
    {
      "name": "．股份资本的增加",
      "page_start": 267,
      "page_end": 267
    },
    {
      "name": "第十五章 规律的内部矛盾的展开",
      "page_start": 269,
      "page_end": 296
    },
    {
      "name": "．生产扩大和价值增殖之间的冲突",
      "page_start": 275,
      "page_end": 275
    },
    {
      "name": "第十六章 商品经营资本",
      "page_start": 297,
      "page_end": 312
    },
    {
      "name": "第十七章 商业利润",
      "page_start": 313,
      "page_end": 337
    },
    {
      "name": "第十八章 商人资本的周转。价格",
      "page_start": 338,
      "page_end": 351
    },
    {
      "name": "第十九章 货币经营资本",
      "page_start": 352,
      "page_end": 360
    },
    {
      "name": "第二十章 关于商人资本的历史考察",
      "page_start": 361,
      "page_end": 376
    },
    {
      "name": "第二十一章 生息资本",
      "page_start": 377,
      "page_end": 400
    },
    {
      "name": "第二十二章 利润的分割。利息率。“自然”利息率",
      "page_start": 401,
      "page_end": 414
    },
    {
      "name": "第二十三章 利息和企业主收入",
      "page_start": 415,
      "page_end": 439
    },
    {
      "name": "第二十四章 资本关系在生息资本形式上的外表化",
      "page_start": 440,
      "page_end": 449
    },
    {
      "name": "第二十五章 信用和虚拟资本",
      "page_start": 450,
      "page_end": 467
    },
    {
      "name": "第二十六章 货币资本的积累，它对利息率的影响",
      "page_start": 468,
      "page_end": 491
    },
    {
      "name": "第二十七章 信用在资本主义生产中的作用",
      "page_start": 492,
      "page_end": 499
    },
    {
      "name": "第二十八章 流通手段和资本。图克和富拉顿的见解",
      "page_start": 500,
      "page_end": 522
    },
    {
      "name": "《资本论》第三卷德文第一版的扉页",
      "page_start": 5,
      "page_end": 5
    },
    {
      "name": "马克思《资本论》第三卷手稿的第一页",
      "page_start": 31,
      "page_end": 31
    },
    {
      "name": "秘书抄写的《资本论》第三卷第一页，上面有恩格斯所作的补充和校正",
      "page_start": 35,
      "page_end": 35
    }
  ]
}