{
  "volume": "第26卷（上）",
  "title": "第26卷",
  "_comment": "仅一级目录，从目录页自动生成，请人工检查",
  "sections": [
    {
      "name": "剩余价值理论（《资本论》第四卷）第 一 册［《剩余价值理论》手稿目录］",
      "page_start": 3,
      "page_end": 6
    },
    {
      "name": "［总的评论］",
      "page_start": 7,
      "page_end": 7
    },
    {
      "name": "插  图卡·马克思《剩余价值理论》手稿的第一页 （1861—8163年手稿第本的开头）",
      "page_start": 9,
      "page_end": 9
    },
    {
      "name": "［第一章］ 詹姆斯·斯图亚特爵士［区分“让渡利润”和财富的绝对增加］",
      "page_start": 11,
      "page_end": 14
    },
    {
      "name": "［第二章］ 重农学派",
      "page_start": 15,
      "page_end": 45
    },
    {
      "name": "卡·马克思《剩余价值理论》手稿的一页，上面有弗·恩格斯的 修改（在本页末）",
      "page_start": 17,
      "page_end": 17
    },
    {
      "name": "［第三章］ 亚当·斯密",
      "page_start": 46,
      "page_end": 141
    },
    {
      "name": "［（01）］研究年利润和年工资怎样才能购买一年内生产的、除利润和工资外还包含不变资本的商品",
      "page_start": 89,
      "page_end": 89
    },
    {
      "name": "［第四章］ 关于生产劳动和非生产劳动的理论",
      "page_start": 142,
      "page_end": 381
    },
    {
      "name": "［（7）热］尔门·加尔涅［把斯密和重农学派的理论庸俗化］",
      "page_start": 176,
      "page_end": 176
    },
    {
      "name": "［（8）］沙尔·加尼耳［关于交换和交换价值的重商主义观点。　　把一切得到报酬的劳动都纳入生产劳动的概念］",
      "page_start": 201,
      "page_end": 201
    },
    {
      "name": "［（01）］收入和资本的交换［简单再生产条件下年产品总量的（ｃ）资本同资本的交换］",
      "page_start": 233,
      "page_end": 233
    },
    {
      "name": "［（11费）里］埃［费里埃对斯密的生产劳动和资本积累理论的　　关于“生产劳动者”的见解中的庸俗成分］",
      "page_start": 258,
      "page_end": 258
    },
    {
      "name": "［（12罗）德］戴尔伯爵［把统治阶级看成各种最重要生产劳动　　的代表的辩护论观点］",
      "page_start": 272,
      "page_end": 272
    },
    {
      "name": "［（14德）斯］杜特·德·特拉西伯爵［关于利润起源的庸俗见　　解。宣称“产业资本家”是唯一的最高意义上的生产劳动者］",
      "page_start": 277,
      "page_end": 277
    },
    {
      "name": "［（16昂）利］·施托尔希［对物质生产和精神生产相互关系问　　题的反历史态度。关于统治阶级的“非物质劳动”的见解］",
      "page_start": 294,
      "page_end": 294
    },
    {
      "name": "［（17纳）骚］·西尼耳［宣称对资产阶级有用的一切职能都　　是生产的。对资产阶级和资产阶级国家阿谀奉承］",
      "page_start": 299,
      "page_end": 299
    },
    {
      "name": "［（81）］佩·罗西［对经济现象的社会形式的忽视。关于　　非生产劳动者“节约劳动”的庸俗见解］",
      "page_start": 304,
      "page_end": 304
    },
    {
      "name": "［第五章］ 奈克尔［试图把资本主义制度下的阶级对立描绘成贫富之间的对立］",
      "page_start": 319,
      "page_end": 322
    },
    {
      "name": "［第六章］ 魁奈的经济表（插入部分）",
      "page_start": 323,
      "page_end": 366
    },
    {
      "name": "卡·马克思《剩余价值理论》手稿的一页，上面有魁奈《经济表》 的图解",
      "page_start": 325,
      "page_end": 325
    },
    {
      "name": "［第七章］ 兰盖［对关于工人“自由”的资产阶级自由主义观点的最初批判］",
      "page_start": 367,
      "page_end": 373
    },
    {
      "name": "附  录［（1霍）布斯论劳动，论价值，论科学的经济作用］",
      "page_start": 377,
      "page_end": 377
    },
    {
      "name": "［（2）历］史方面：配第［对于非生产职业的否定态度。劳动价值论的萌芽。在价值论的基础上说明工资、地租、土地价格和利息的尝试］",
      "page_start": 378,
      "page_end": 388
    },
    {
      "name": "［（3）配］第、达德利·诺思爵士、洛克",
      "page_start": 389,
      "page_end": 389
    },
    {
      "name": "［（4）洛］克［从资产阶级自然法理论观点来解释地租和利息］",
      "page_start": 390,
      "page_end": 393
    },
    {
      "name": "［（5）诺］思［作为资本的货币。商业的发展是利率下降的原因］",
      "page_start": 394,
      "page_end": 398
    },
    {
      "name": "［（6贝）克莱论勤劳是财富的源泉］",
      "page_start": 399,
      "page_end": 399
    },
    {
      "name": "［（7）休］谟和马西",
      "page_start": 400,
      "page_end": 404
    },
    {
      "name": "［（8）对论重农学派的各章的补充］",
      "page_start": 405,
      "page_end": 407
    },
    {
      "name": "［（9）重农学派的追随者毕阿伯爵对土地贵族的赞美］",
      "page_start": 408,
      "page_end": 409
    },
    {
      "name": "［（01）从重农学派的观点出发反驳土地贵族（英国的一个匿名作者）］",
      "page_start": 410,
      "page_end": 414
    },
    {
      "name": "［（1关1）于一切职业都具有生产性的辩护论见解］",
      "page_start": 415,
      "page_end": 417
    },
    {
      "name": "［（12资）本］的生产性。生产劳动和非生产劳动",
      "page_start": 418,
      "page_end": 445
    },
    {
      "name": "［（13资）本《论》第一部分和第三部分的计划草稿］",
      "page_start": 446,
      "page_end": 448
    },
    {
      "name": "注释",
      "page_start": 451,
      "page_end": 476
    },
    {
      "name": "人名索引",
      "page_start": 477,
      "page_end": 484
    },
    {
      "name": "本书中引用和提到的著作索引",
      "page_start": 485,
      "page_end": 496
    }
  ]
}